corona_tracker_india/__init__.py
corona_tracker_india/tracker.py
corona_tracker_india-0.1.4.dist-info/METADATA
corona_tracker_india-0.1.4.dist-info/WHEEL
corona_tracker_india-0.1.4.dist-info/top_level.txt
corona_tracker_india-0.1.4.dist-info/RECORD
