Metadata-Version: 2.1
Name: corona-tracker-india
Version: 0.1.4
Summary: Corona disease tracker for India
Home-page: https://github.com/arsharaj/corona-tracker-india
Author: Arsharaj Chauhan
Author-email: arsharajchauhan343@gmail.com
License: GPL
Keywords: corona disease tracker for india
Platform: UNKNOWN
Classifier: Development Status :: 4 - Beta
Classifier: Environment :: Console
Classifier: Intended Audience :: Healthcare Industry
Classifier: License :: OSI Approved :: GNU General Public License (GPL)
Classifier: Operating System :: OS Independent
Classifier: Programming Language :: Python
Classifier: Topic :: Internet
Requires-Python: >=3.6
Requires-Dist: beautifulsoup4
Requires-Dist: tabulate
Requires-Dist: requests
